<odoo>
    <data>
        <template id="custom_show_default_code.product_page" name="custom_show_default_code.product_page" inherit_id="website_sale.product_price">
            <xpath expr="//h3[@class='css_editable_mode_hidden']" position="after">
                <h3 class="custom_default_sku"></h3>
            </xpath>
        </template>
<!--
        <template id="listing">
          <ul>
            <li t-foreach="objects" t-as="object">
              <a t-attf-href="#{ root }/objects/#{ object.id }">
                <t t-esc="object.display_name"/>
              </a>
            </li>
          </ul>
        </template>
        <template id="object">
          <h1><t t-esc="object.display_name"/></h1>
          <dl>
            <t t-foreach="object._fields" t-as="field">
              <dt><t t-esc="field"/></dt>
              <dd><t t-esc="object[field]"/></dd>
            </t>
          </dl>
        </template>
-->
    </data>
</odoo>